faiss_apis/__init__.py
faiss_apis/faiss_pb2.py
faiss_apis/faiss_pb2_grpc.py
faiss_server_client-1.0.0.dist-info/METADATA
faiss_server_client-1.0.0.dist-info/WHEEL
faiss_server_client-1.0.0.dist-info/top_level.txt
faiss_server_client-1.0.0.dist-info/RECORD
