Metadata-Version: 2.1
Name: faiss-server-client
Version: 1.0.0
Summary: faiss-server
Home-page: https://github.com/pypa/sampleproject
Author: fly_cat
Author-email: nzpflycat@gmail.com
